grance/__init__.py
grance/grance.py
grance/util/__init__.py
grance/util/subr.py
grance-0.1.0.dist-info/LICENSE
grance-0.1.0.dist-info/METADATA
grance-0.1.0.dist-info/WHEEL
grance-0.1.0.dist-info/RECORD
